max_yaml.py
max_yaml-0.1.0.dist-info/entry_points.txt
max_yaml-0.1.0.dist-info/LICENSE
max_yaml-0.1.0.dist-info/WHEEL
max_yaml-0.1.0.dist-info/METADATA
max_yaml-0.1.0.dist-info/RECORD
