Metadata-Version: 2.1
Name: max-yaml
Version: 0.1.0
Summary: Creates dump, dumps, load, and load function for yaml doc based on the json stdlib.
License: MIT
Author: maxludden
Author-email: dev@maxludden.com
Requires-Python: >=3.10,<4.0
Classifier: License :: OSI Approved :: MIT License
Classifier: Programming Language :: Python :: 3
Classifier: Programming Language :: Python :: 3.10
Classifier: Programming Language :: Python :: 3.11
Requires-Dist: maxconsole (>=0.4.0,<0.5.0)
Requires-Dist: pyaml (>=21.10.1,<22.0.0)
